mca/__init__.py
mca/biome.py
mca/block.py
mca/chunk.py
mca/empty_chunk.py
mca/empty_region.py
mca/empty_section.py
mca/errors.py
mca/nbt.py
mca/raw_section.py
mca/region.py
mcapy-0.9.1.dist-info/LICENSE
mcapy-0.9.1.dist-info/METADATA
mcapy-0.9.1.dist-info/WHEEL
mcapy-0.9.1.dist-info/top_level.txt
mcapy-0.9.1.dist-info/RECORD
