Metadata-Version: 2.1
Name: mcapy
Version: 0.9.1
Summary: A Minecraft MCA file reader/writer
Home-page: https://github.com/wensheng/mcapy
Author: wensheng
Classifier: Programming Language :: Python :: 3
Classifier: License :: OSI Approved :: MIT License
Classifier: Operating System :: OS Independent
License-File: LICENSE
